pypdf_utils/__init__.py
pypdf_utils/join.py
pypdf_utils/mkbooklet.py
pypdf_utils/remove.py
pypdf_utils-0.0.1.dist-info/LICENSE
pypdf_utils-0.0.1.dist-info/METADATA
pypdf_utils-0.0.1.dist-info/WHEEL
pypdf_utils-0.0.1.dist-info/entry_points.txt
pypdf_utils-0.0.1.dist-info/top_level.txt
pypdf_utils-0.0.1.dist-info/RECORD
