Metadata-Version: 2.1
Name: pypdf-utils
Version: 0.0.1
Summary: Utility scripts for PDF manipulation using PyPDF2
Author-email: Guilherme Lima <guilima10@gmail.com>
License: MIT License        
Project-URL: Homepage, https://github.com/limaa/pypdf-utils
Project-URL: Source Code, https://github.com/limaa/pypdf-utils
License-File: LICENSE
Requires-Dist: PyPDF2 (~=2.4.2)
